tests/__init__.py
tests/test_profile.py
tests/test_set_paths.py
torchprof/__init__.py
torchprof/display.py
torchprof/profile.py
torchprof-1.4.0.dist-info/LICENSE
torchprof-1.4.0.dist-info/METADATA
torchprof-1.4.0.dist-info/WHEEL
torchprof-1.4.0.dist-info/top_level.txt
torchprof-1.4.0.dist-info/RECORD
