Metadata-Version: 2.1
Name: torchprof
Version: 1.4.0
Summary: Measure neural network device specific metrics (latency, flops, etc.)
Home-page: https://github.com/awwong1/torchprof
Author: Alexander Wong
Author-email: alex@udia.ca
License: MIT
Platform: UNKNOWN
Classifier: License :: OSI Approved :: MIT License
Classifier: Operating System :: OS Independent
Classifier: Programming Language :: Python :: 3
Classifier: Programming Language :: Python :: 3.5
Classifier: Programming Language :: Python :: 3.6
Classifier: Programming Language :: Python :: 3.7
Classifier: Programming Language :: Python :: 3.8
Requires-Dist: torch (<1.9,>=1.1.0)
